{
    "products": [
        {
            "id": 1,
            "title":"Vintage Leica M3 Camera",
            "description": "Camera",
            "currentBidPrice": 2999,
            "timeLeft": "1 Days left",
            "bidsCount": 1,
            "image": "https://i.ibb.co.com/Q406vNJ/Bid1-min.png"
        },
        {
            "id": 2,
            "title":"1965 Gibson SG Standard Electric Guitar",
            "description": "Guitar",
            "currentBidPrice": 7999,
            "timeLeft": "4 Days left",
            "bidsCount": 1,
            "image": "https://i.ibb.co.com/7FBs2yJ/Bid2-min.png"
        },
        {
            "id": 3,
            "title":"Original Apple Macintosh 128K (1984)",
            "description": "Apple",
            "currentBidPrice": 6999,
            "timeLeft": "5 Days left",
            "bidsCount": 1,
            "image": "https://i.ibb.co.com/60zBnpR6/Bid3-min.png"
        },
        {
            "id": 4,
            "title":"Rolex Submariner 16610",
            "description": "Rolex",
            "currentBidPrice": 1999,
            "timeLeft": "3 Days left",
            "bidsCount": 1,
            "image": "https://i.ibb.co.com/MyLsQG2P/Bid4-min.png"
        },
        {
            "id": 5,
            "title":"First Edition 'The Great Gatsby' by F.Scott Fizgerald",
            "description": "Gatsby",
            "currentBidPrice": 3999,
            "timeLeft": "2 Days left",
            "bidsCount": 1,
            "image": "https://i.ibb.co.com/b54fLZf9/Bid5-min.png"
        },
        {
            "id": 6,
            "title":"Mid-Century Modern Eames Lounge Chair",
            "description": "Chair",
            "currentBidPrice": 5999,
            "timeLeft": "7 Days left",
            "bidsCount": 1,
            "image": "https://i.ibb.co.com/5VqqSX6/Bid6-min.png"
        },
        {
            "id": 7,
            "title":"Banksy Original Screen Print",
            "description": "Banksy",
            "currentBidPrice": 4999,
            "timeLeft": "6 Days left",
            "bidsCount": 1,
            "image": "https://i.ibb.co.com/k2drnmyT/Bid7-min.png"
        }
    ]
}

